packagedcode_msitools/__init__.py
packagedcode_msitools/bin/msiinfo
packagedcode_msitools/licenses/apache-2.0.LICENSE
packagedcode_msitools/licenses/lgpl-2.1-plus.LICENSE
packagedcode_msitools-0.101.210706.dist-info/METADATA
packagedcode_msitools-0.101.210706.dist-info/README.rst
packagedcode_msitools-0.101.210706.dist-info/WHEEL
packagedcode_msitools-0.101.210706.dist-info/apache-2.0.LICENSE
packagedcode_msitools-0.101.210706.dist-info/entry_points.txt
packagedcode_msitools-0.101.210706.dist-info/gpl-2.0-plus.LICENSE
packagedcode_msitools-0.101.210706.dist-info/lgpl-2.1-plus.LICENSE
packagedcode_msitools-0.101.210706.dist-info/mit.LICENSE
packagedcode_msitools-0.101.210706.dist-info/packagedcode_msitools.ABOUT
packagedcode_msitools-0.101.210706.dist-info/top_level.txt
packagedcode_msitools-0.101.210706.dist-info/RECORD
