Metadata-Version: 2.1
Name: packagedcode-msitools
Version: 0.101.210706
Summary: A ScanCode path provider plugin to provide prebuilt binaries from msitools
Home-page: https://github.com/aboutcode-org/scancode-plugins
Author: nexB
Author-email: info@aboutcode.org
License: apache-2.0 AND lgpl-2.1-plus AND gpl-2.0-plus AND mit
Keywords: open source,msitools,scancode,packagedcode
Classifier: Development Status :: 5 - Production/Stable
Classifier: Intended Audience :: Developers
Classifier: Topic :: Utilities
License-File: apache-2.0.LICENSE
License-File: gpl-2.0-plus.LICENSE
License-File: lgpl-2.1-plus.LICENSE
License-File: mit.LICENSE
License-File: packagedcode_msitools.ABOUT
License-File: README.rst
Requires-Dist: plugincode
